Workbook
Name Slicer_Coles_Forecast: #N/A
Name Slicer_State: #N/A
Name Slicer_Targeted_Quarter: #N/A

Sheet ColesSalesData
B1: Coles_StoreIDNo | C1: Expec_Revenue | D1: Gross_Sale | E1: Sales_Cost | F1: Targeted_Quarter | G1: Coles_Forecast
A2: 1 | B2: C524 | C2: 39 | D2: 56 | E2: 6 | F2: Q2 2023 | G2: On Target
A3: 2 | B3: C624 | C3: 22 | D3: 55 | E3: 7 | F3: Q1 2023 | G3: On Target
A4: 3 | B4: C460 | C4: 36 | D4: 51 | E4: 7 | F4: Q1 2023 | G4: On Target
A5: 4 | B5: C708 | C5: 48 | D5: 50 | E5: 10 | F5: Q1 2023 | G5: Below Target
A6: 5 | B6: C647 | C6: 23 | D6: 39 | E6: 18 | F6: Q2 2023 | G6: Below Target
A7: 6 | B7: C713 | C7: 38 | D7: 84 | E7: 15 | F7: Q2 2023 | G7: On Target
A8: 7 | B8: C308 | C8: 31 | D8: 55 | E8: 10 | F8: Q1 2023 | G8: On Target
A9: 8 | B9: C494 | C9: 38 | D9: 44 | E9: 8 | F9: Q1 2023 | G9: Below Target
A10: 9 | B10: C656 | C10: 30 | D10: 39 | E10: 10 | F10: Q2 2023 | G10: Below Target
A11: 10 | B11: C280 | C11: 44 | D11: 26 | E11: 15 | F11: Q1 2023 | G11: Below Target
A12: 11 | B12: C738 | C12: 34 | D12: 29 | E12: 13 | F12: Q1 2023 | G12: Below Target
A13: 12 | B13: C164 | C13: 49 | D13: 45 | E13: 9 | F13: Q2 2023 | G13: Below Target
... A31: 30 | B31: C419 | C31: 25 | D31: 42 | E31: 13 | F31: Q2 2023 | G31: On Target
A32: 31 | B32: C443 | C32: 37 | D32: 57 | E32: NA | F32: Q1 2023 | G32: NA
A33: 32 | B33: C640 | C33: 42 | D33: 55 | E33: 5 | F33: Q1 2023 | G33: On Target
A34: 33 | B34: C317 | C34: 43 | D34: 31 | E34: 8 | F34: Q2 2023 | G34: Below Target
A35: 34 | B35: C207 | C35: 23 | D35: 36 | E35: 11 | F35: Q2 2023 | G35: On Target
A36: 35 | B36: C336 | C36: 41 | D36: 47 | E36: 7 | F36: Q2 2023 | G36: Below Target
A37: 36 | B37: C309 | C37: 40 | D37: 29 | E37: 5 | F37: Q2 2023 | G37: Below Target
A38: 37 | B38: C163 | C38: 30 | D38: 59 | E38: 9 | F38: Q2 2023 | G38: On Target
A39: 38 | B39: C461 | C39: 29 | D39: 50 | E39: 20 | F39: Q1 2023 | G39: On Target
A40: 39 | B40: C628 | C40: 34 | D40: 38 | E40: 6 | F40: Q1 2023 | G40: Below Target
A41: 40 | B41: C759 | C41: 38 | D41: 32 | E41: 10 | F41: Q1 2023 | G41: Below Target
A42: 41 | B42: C463 | C42: 24 | D42: 30 | E42: 10 | F42: Q1 2023 | G42: Below Target
A43: 42 | B43: C203 | C43: 48 | D43: 55 | E43: 7 | F43: Q1 2023 | G43: On Target
A44: 43 | B44: C245 | C44: 28 | D44: 50 | E44: 7 | F44: Q1 2023 | G44: On Target
... A55: 54 | B55: C493 | C55: 44 | D55: 54 | E55: 10 | F55: Q1 2023 | G55: On Target
A56: 55 | B56: C583 | C56: 43 | D56: 29 | E56: NA | F56: Q2 2023 | G56: NA
A57: 56 | B57: C794 | C57: 34 | D57: 35 | E57: 5 | F57: Q1 2023 | G57: Below Target
A58: 57 | B58: C431 | C58: 45 | D58: 42 | E58: 9 | F58: Q2 2023 | G58: Below Target
A59: 58 | B59: C348 | C59: 27 | D59: 40 | E59: 13 | F59: Q1 2023 | G59: On Target
A60: 59 | B60: C694 | C60: 28 | D60: 39 | E60: 9 | F60: Q1 2023 | G60: On Target
A61: 60 | B61: C218 | C61: 24 | D61: 43 | E61: 9 | F61: Q1 2023 | G61: On Target
A62: 61 | B62: C349 | C62: 29 | D62: 43 | E62: 12 | F62: Q2 2023 | G62: On Target
A63: 62 | B63: C674 | C63: 36 | D63: 47 | E63: 10 | F63: Q2 2023 | G63: On Target
A64: 63 | B64: C773 | C64: 48 | D64: 50 | E64: 6 | F64: Q2 2023 | G64: Below Target
A65: 64 | B65: C182 | C65: 42 | D65: 56 | E65: 13 | F65: Q1 2023 | G65: On Target
A66: 65 | B66: C664 | C66: 41 | D66: 41 | E66: 11 | F66: Q2 2023 | G66: Below Target
A67: 66 | B67: C192 | C67: 50 | D67: 36 | E67: 11 | F67: Q2 2023 | G67: Below Target
A68: 67 | B68: C366 | C68: 26 | D68: 59 | E68: 11 | F68: Q1 2023 | G68: On Target
... A101: 100 | B101: C314 | C101: 47 | D101: 40 | E101: 7 | F101: Q1 2023 | G101: Below Target
A102: 101 | B102: C258 | C102: 40 | D102: 53 | E102: NA | F102: Q1 2023 | G102: NA
A103: 102 | B103: C476 | C103: 21 | D103: 59 | E103: 13 | F103: Q2 2023 | G103: On Target
A104: 103 | B104: C549 | C104: 41 | D104: 49 | E104: 9 | F104: Q2 2023 | G104: Below Target
A105: 104 | B105: C148 | C105: 34 | D105: 57 | E105: 14 | F105: Q2 2023 | G105: On Target
A106: 105 | B106: C200 | C106: 44 | D106: 45 | E106: 8 | F106: Q1 2023 | G106: Below Target
A107: 106 | B107: C294 | C107: 38 | D107: 30 | E107: 12 | F107: Q1 2023 | G107: Below Target
A108: 107 | B108: C751 | C108: 26 | D108: 58 | E108: 14 | F108: Q1 2023 | G108: On Target
A109: 108 | B109: C652 | C109: 35 | D109: 37 | E109: 13 | F109: Q2 2023 | G109: Below Target
A110: 109 | B110: C104 | C110: 36 | D110: 40 | E110: 13 | F110: Q1 2023 | G110: Below Target
A111: 110 | B111: C269 | C111: 44 | D111: 31 | E111: 9 | F111: Q2 2023 | G111: Below Target
A112: 111 | B112: C266 | C112: 35 | D112: 36 | E112: 7 | F112: Q2 2023 | G112: Below Target
A113: 112 | B113: C778 | C113: 39 | D113: 39 | E113: 10 | F113: Q2 2023 | G113: Below Target
A114: 113 | B114: C698 | C114: 43 | D114: 37 | E114: 5 | F114: Q1 2023 | G114: Below Target
... A129: 128 | B129: C418 | C129: 34 | D129: 29 | E129: 14 | F129: Q1 2023 | G129: Below Target
A130: 129 | B130: C703 | C130: 30 | D130: 54 | E130: NA | F130: Q1 2023 | G130: NA
A131: 130 | B131: C256 | C131: 24 | D131: 60 | E131: NA | F131: Q2 2023 | G131: NA
A132: 131 | B132: C472 | C132: 36 | D132: 42 | E132: 10 | F132: Q1 2023 | G132: Below Target
A133: 132 | B133: C284 | C133: 43 | D133: 53 | E133: 11 | F133: Q2 2023 | G133: Below Target
A134: 133 | B134: C321 | C134: 46 | D134: 28 | E134: 12 | F134: Q1 2023 | G134: Below Target
A135: 134 | B135: C757 | C135: 37 | D135: 32 | E135: 11 | F135: Q2 2023 | G135: Below Target
A136: 135 | B136: C666 | C136: 32 | D136: 35 | E136: 15 | F136: Q2 2023 | G136: Below Target
A137: 136 | B137: C276 | C137: 35 | D137: 48 | E137: 9 | F137: Q2 2023 | G137: On Target
A138: 137 | B138: C642 | C138: 30 | D138: 53 | E138: 12 | F138: Q1 2023 | G138: On Target
A139: 138 | B139: C198 | C139: 25 | D139: 30 | E139: 5 | F139: Q2 2023 | G139: On Target
A140: 139 | B140: C462 | C140: 30 | D140: 31 | E140: 4 | F140: Q2 2023 | G140: Below Target
A141: 140 | B141: C345 | C141: 39 | D141: 29 | E141: 4 | F141: Q2 2023 | G141: Below Target
A142: 141 | B142: C489 | C142: 39 | D142: 48 | E142: 9 | F142: Q2 2023 | G142: On Target
A143: 142 | B143: C761 | C143: 27 | D143: 55 | E143: 14 | F143: Q2 2023 | G143: On Target
... A209: 208 | B209: C581 | C209: 35 | D209: 52 | E209: 15 | F209: Q1 2023 | G209: On Target
A210: 209 | B210: C411 | C210: 22 | D210: 49 | E210: NA | F210: Q2 2023 | G210: NA
A211: 210 | B211: C453 | C211: 43 | D211: 28 | E211: 6 | F211: Q1 2023 | G211: Below Target
A212: 211 | B212: C279 | C212: 31 | D212: 51 | E212: 7 | F212: Q1 2023 | G212: On Target
A213: 212 | B213: C768 | C213: 41 | D213: 36 | E213: 7 | F213: Q2 2023 | G213: Below Target
A214: 213 | B214: C532 | C214: 45 | D214: 41 | E214: 10 | F214: Q2 2023 | G214: Below Target
A215: 214 | B215: C334 | C215: 41 | D215: 57 | E215: 9 | F215: Q1 2023 | G215: On Target
A216: 215 | B216: C301 | C216: 25 | D216: 50 | E216: 16 | F216: Q1 2023 | G216: On Target
A217: 216 | B217: C210 | C217: 47 | D217: 31 | E217: 10 | F217: Q1 2023 | G217: Below Target
A218: 217 | B218: C735 | C218: 20 | D218: 48 | E218: 5 | F218: Q1 2023 | G218: On Target
A219: 218 | B219: C684 | C219: 37 | D219: 46 | E219: 6 | F219: Q2 2023 | G219: On Target
A220: 219 | B220: C665 | C220: 44 | D220: 34 | E220: 4 | F220: Q1 2023 | G220: Below Target
A221: 220 | B221: C571 | C221: 44 | D221: 25 | E221: 11 | F221: Q2 2023 | G221: Below Target
A222: 221 | B222: C742 | C222: 27 | D222: 59 | E222: 10 | F222: Q1 2023 | G222: On Target
... A251: 250 | B251: C727 | C251: 30 | D251: 29 | E251: 11 | F251: Q2 2023 | G251: Below Target
A252: 251 | B252: C362 | C252: 42 | D252: 48 | E252: NA | F252: Q2 2023 | G252: NA
A253: 252 | B253: C795 | C253: 22 | D253: 29 | E253: 13 | F253: Q2 2023 | G253: Below Target
A254: 253 | B254: C667 | C254: 26 | D254: 40 | E254: 9 | F254: Q2 2023 | G254: On Target
A255: 254 | B255: C270 | C255: 49 | D255: 38 | E255: 7 | F255: Q1 2023 | G255: Below Target
A256: 255 | B256: C451 | C256: 40 | D256: 41 | E256: 11 | F256: Q1 2023 | G256: Below Target
A257: 256 | B257: C557 | C257: 33 | D257: 47 | E257: 8 | F257: Q2 2023 | G257: On Target
A258: 257 | B258: C563 | C258: 35 | D258: 31 | E258: 8 | F258: Q1 2023 | G258: Below Target
A259: 258 | B259: C490 | C259: 30 | D259: 52 | E259: 13 | F259: Q2 2023 | G259: On Target
A260: 259 | B260: C650 | C260: 45 | D260: 54 | E260: 8 | F260: Q2 2023 | G260: On Target
A261: 260 | B261: C142 | C261: 45 | D261: 54 | E261: 7 | F261: Q2 2023 | G261: On Target
A262: 261 | B262: C253 | C262: 29 | D262: 53 | E262: 9 | F262: Q2 2023 | G262: On Target
A263: 262 | B263: C162 | C263: 29 | D263: 26 | E263: 9 | F263: Q2 2023 | G263: Below Target
A264: 263 | B264: C449 | C264: 30 | D264: 55 | E264: 10 | F264: Q2 2023 | G264: On Target
... A285: 284 | B285: C513 | C285: 48 | D285: 36 | E285: 17 | F285: Q1 2023 | G285: Below Target
A286: 285 | B286: C747 | C286: 37 | D286: 36 | E286: NA | F286: Q1 2023 | G286: NA
...

Sheet ColesStoreData
B1: Coles_StoreID | C1: Store_Location | D1: Customer_Count | E1: Staff_Count | F1: Store_Area
A2: 1 | B2: C524 | C2: QLD | D2: 18445 | E2: 36 | F2: 2500
A3: 2 | B3: C624 | C3: NSW | D3: 40535 | E3: 37 | F3: 2500
A4: 3 | B4: C460 | C4: VIC | D4: 6146 | E4: 19 | F4: 1900
A5: 4 | B5: C708 | C5: SA | D5: 9151 | E5: 23 | F5: 1900
A6: 5 | B6: C647 | C6: NSW | D6: 9308 | E6: 23 | F6: 1700
A7: 6 | B7: C713 | C7: QLD | D7: 58430 | E7: 27 | F7: 2500
A8: 7 | B8: C308 | C8: VIC | D8: 38603 | E8: 31 | F8: 2500
A9: 8 | B9: C494 | C9: QLD | D9: 9545 | E9: 19 | F9: 1700
A10: 9 | B10: C656 | C10: VIC | D10: 9357 | E10: 17 | F10: 1700
A11: 10 | B11: C280 | C11: WA | D11: 8389 | E11: 22 | F11: 1700
A12: 11 | B12: C738 | C12: VIC | D12: 8953 | E12: 18 | F12: 1700
A13: 12 | B13: C164 | C13: ACT | D13: 7927 | E13: 20 | F13: 1900
... A23: 22 | B23: C672 | C23: SA | D23: 9850 | E23: 26 | F23: 1700
A24: 23 | B24: C313 | C24: NSW | D24: NA | E24: 39 | F24: 2500
A25: 24 | B25: C450 | C25: NSW | D25: 7566 | E25: 16 | F25: 1900
A26: 25 | B26: C699 | C26: VIC | D26: 7221 | E26: 26 | F26: 1900
A27: 26 | B27: C760 | C27: NSW | D27: 9149 | E27: 19 | F27: 1700
A28: 27 | B28: C174 | C28: NSW | D28: 7358 | E28: 20 | F28: 1700
A29: 28 | B29: C344 | C29: VIC | D29: 9657 | E29: 23 | F29: 1700
A30: 29 | B30: C382 | C30: NSW | D30: 7431 | E30: 18 | F30: 1900
A31: 30 | B31: C419 | C31: NSW | D31: 7250 | E31: 15 | F31: 1700
A32: 31 | B32: C443 | C32: QLD | D32: 8035 | E32: 32 | F32: 2500
A33: 32 | B33: C640 | C33: QLD | D33: 50859 | E33: 25 | F33: 2500
A34: 33 | B34: C317 | C34: QLD | D34: 9122 | E34: 26 | F34: 1700
A35: 34 | B35: C207 | C35: NSW | D35: NA | E35: 15 | F35: 1700
A36: 35 | B36: C336 | C36: QLD | D36: 9741 | E36: 25 | F36: 1900
A37: 36 | B37: C309 | C37: QLD | D37: 6948 | E37: 25 | F37: 1700
A38: 37 | B38: C163 | C38: VIC | D38: 25397 | E38: 33 | F38: 2700
A39: 38 | B39: C461 | C39: VIC | D39: 9534 | E39: 16 | F39: 1900
A40: 39 | B40: C628 | C40: VIC | D40: 9912 | E40: 24 | F40: 1700
A41: 40 | B41: C759 | C41: QLD | D41: 7869 | E41: 16 | F41: 1700
A42: 41 | B42: C463 | C42: NSW | D42: 9097 | E42: 19 | F42: 1700
A43: 42 | B43: C203 | C43: SA | D43: 22370 | E43: 30 | F43: 2500
A44: 43 | B44: C245 | C44: NSW | D44: 8363 | E44: 20 | F44: 1900
A45: 44 | B45: C562 | C45: VIC | D45: 9242 | E45: 25 | F45: 1700
A46: 45 | B46: C442 | C46: ACT | D46: 9026 | E46: 19 | F46: 1700
A47: 46 | B47: C776 | C47: NSW | D47: 9015 | E47: 26 | F47: 1700
... A60: 59 | B60: C694 | C60: NSW | D60: 6624 | E60: 23 | F60: 1700
A61: 60 | B61: C218 | C61: NSW | D61: NA | E61: 25 | F61: 1700
A62: 61 | B62: C349 | C62: VIC | D62: 8337 | E62: 23 | F62: 1700
A63: 62 | B63: C674 | C63: VIC | D63: 7851 | E63: 25 | F63: 1900
A64: 63 | B64: C773 | C64: SA | D64: 8173 | E64: 23 | F64: 1900
A65: 64 | B65: C182 | C65: QLD | D65: 51428 | E65: 35 | F65: 2500
A66: 65 | B66: C664 | C66: QLD | D66: 9593 | E66: 23 | F66: 1700
A67: 66 | B67: C192 | C67: TAS | D67: 7207 | E67: 21 | F67: 1700
A68: 67 | B68: C366 | C68: NSW | D68: 28776 | E68: 28 | F68: 2700
A69: 68 | B69: C682 | C69: NSW | D69: 8926 | E69: 15 | F69: 1900
A70: 69 | B70: C597 | C70: VIC | D70: 7378 | E70: 15 | F70: 1900
A71: 70 | B71: C341 | C71: WA | D71: 6819 | E71: 26 | F71: 1900
A72: 71 | B72: C484 | C72: NSW | D72: 6334 | E72: 22 | F72: 1700
A73: 72 | B73: C293 | C73: VIC | D73: 7261 | E73: 23 | F73: 1700
... A86: 85 | B86: C591 | C86: NSW | D86: 9655 | E86: 15 | F86: 1700
A87: 86 | B87: C500 | C87: QLD | D87: NA | E87: 24 | F87: 1700
A88: 87 | B88: C634 | C88: QLD | D88: 8638 | E88: 18 | F88: 1900
A89: 88 | B89: C456 | C89: VIC | D89: 7789 | E89: 19 | F89: 1700
A90: 89 | B90: C800 | C90: VIC | D90: 9872 | E90: 26 | F90: 1700
A91: 90 | B91: C138 | C91: QLD | D91: NA | E91: 27 | F91: 2500
A92: 91 | B92: C705 | C92: VIC | D92: NA | E92: 15 | F92: 1900
A93: 92 | B93: C523 | C93: NSW | D93: 8372 | E93: 26 | F93: 1900
A94: 93 | B94: C124 | C94: VIC | D94: 6867 | E94: 20 | F94: 1700
A95: 94 | B95: C515 | C95: QLD | D95: 8007 | E95: 25 | F95: 1900
A96: 95 | B96: C355 | C96: VIC | D96: 8862 | E96: 20 | F96: 1700
A97: 96 | B97: C459 | C97: NSW | D97: 9265 | E97: 16 | F97: 1700
A98: 97 | B98: C739 | C98: NSW | D98: 6680 | E98: 16 | F98: 1700
A99: 98 | B99: C303 | C99: VIC | D99: 7577 | E99: 25 | F99: 1900
A100: 99 | B100: C234 | C100: NSW | D100: 8944 | E100: 16 | F100: 1900
A101: 100 | B101: C314 | C101: SA | D101: 8372 | E101: 15 | F101: 1700
A102: 101 | B102: C258 | C102: QLD | D102: 9178 | E102: 20 | F102: 1900
A103: 102 | B103: C476 | C103: NSW | D103: 24760 | E103: 38 | F103: 2700
A104: 103 | B104: C549 | C104: QLD | D104: 8641 | E104: 20 | F104: 1900
... A116: 115 | B116: C623 | C116: NSW | D116: 6700 | E116: 21 | F116: 1700
A117: 116 | B117: C121 | C117: WA | D117: NA | E117: 36 | F117: 2700
A118: 117 | B118: C639 | C118: VIC | D118: 9312 | E118: 17 | F118: 1700
A119: 118 | B119: C265 | C119: WA | D119: NA | E119: 15 | F119: 1700
A120: 119 | B120: C648 | C120: VIC | D120: 8566 | E120: 19 | F120: 1700
A121: 120 | B121: C725 | C121: NSW | D121: 9147 | E121: 26 | F121: 1900
A122: 121 | B122: C775 | C122: SA | D122: 6713 | E122: 20 | F122: 1700
A123: 122 | B123: C593 | C123: QLD | D123: 8214 | E123: 22 | F123: 1900
A124: 123 | B124: C611 | C124: NSW | D124: 8332 | E124: 15 | F124: 1900
A125: 124 | B125: C302 | C125: NSW | D125: 6156 | E125: 15 | F125: 1700
A126: 125 | B126: C709 | C126: NSW | D126: 6992 | E126: 15 | F126: 1700
A127: 126 | B127: C187 | C127: QLD | D127: 8878 | E127: 26 | F127: 1700
A128: 127 | B128: C637 | C128: VIC | D128: 7704 | E128: 19 | F128: 1900
A129: 128 | B129: C418 | C129: VIC | D129: 9454 | E129: 15 | F129: 1700
A130: 129 | B130: C703 | C130: VIC | D130: 47473 | E130: 34 | F130: 2500
A131: 130 | B131: C256 | C131: NSW | D131: NA | E131: 35 | F131: 2700
A132: 131 | B132: C472 | C132: VIC | D132: 9254 | E132: 19 | F132: 1700
A133: 132 | B133: C284 | C133: QLD | D133: 9413 | E133: 24 | F133: 1900
A134: 133 | B134: C321 | C134: WA | D134: 8423 | E134: 19 | F134: 1700
A135: 134 | B135: C757 | C135: VIC | D135: 9380 | E135: 21 | F135: 1700
A136: 135 | B136: C666 | C136: VIC | D136: 8736 | E136: 23 | F136: 1700
A137: 136 | B137: C276 | C137: VIC | D137: 7259 | E137: 16 | F137: 1900
A138: 137 | B138: C642 | C138: VIC | D138: 7798 | E138: 20 | F138: 1900
A139: 138 | B139: C198 | C139: NSW | D139: 6058 | E139: 19 | F139: 1700
A140: 139 | B140: C462 | C140: VIC | D140: 6399 | E140: 16 | F140: 1700
A141: 140 | B141: C345 | C141: QLD | D141: 8893 | E141: 24 | F141: 1700
A142: 141 | B142: C489 | C142: QLD | D142: 9662 | E142: 25 | F142: 1900
A143: 142 | B143: C761 | C143: NSW | D143: 52103 | E143: 28 | F143: 2500
... A145: 144 | B145: C410 | C145: VIC | D145: 9220 | E145: 17 | F145: 1700
...

Sheet Working Sheet
B1: Coles_StoreIDNo | C1: Expec_Revenue | D1: Gross_Sale | E1: Sales_Cost | F1: Targeted_Quarter | G1: Coles_Forecast | H1: State | I1: Customer_Count | J1: Store_data | K1: Profit | L1: Profit_Margin
A2: 1 | B2: C524 | C2: 39 | D2: 56 | E2: 6 | F2: Q2 2023 | G2: On Target | H2: =VLOOKUP(B2,ColesStoreData!$B:$F,2,0) -> QLD | I2: =VLOOKUP(B2,ColesStoreData!$B:$F,3,0) -> 18445 | J2: =VLOOKUP(B2,ColesStoreData!$B:$F,5,0) -> 2500 | K2: =D2-E2 -> 50 | L2: =K2/D2 -> 0.89285714
A3: 2 | B3: C624 | C3: 22 | D3: 55 | E3: 7 | F3: Q1 2023 | G3: On Target | H3: =VLOOKUP(B3,ColesStoreData!$B:$F,2,0) -> NSW | I3: =VLOOKUP(B3,ColesStoreData!$B:$F,3,0) -> 40535 | J3: =VLOOKUP(B3,ColesStoreData!$B:$F,5,0) -> 2500 | K3: =D3-E3 -> 48 | L3: =K3/D3 -> 0.87272727
A4: 3 | B4: C460 | C4: 36 | D4: 51 | E4: 7 | F4: Q1 2023 | G4: On Target | H4: =VLOOKUP(B4,ColesStoreData!$B:$F,2,0) -> VIC | I4: =VLOOKUP(B4,ColesStoreData!$B:$F,3,0) -> 6146 | J4: =VLOOKUP(B4,ColesStoreData!$B:$F,5,0) -> 1900 | K4: =D4-E4 -> 44 | L4: =K4/D4 -> 0.8627451
A5: 4 | B5: C708 | C5: 48 | D5: 50 | E5: 10 | F5: Q1 2023 | G5: Below Target | H5: =VLOOKUP(B5,ColesStoreData!$B:$F,2,0) -> SA | I5: =VLOOKUP(B5,ColesStoreData!$B:$F,3,0) -> 9151 | J5: =VLOOKUP(B5,ColesStoreData!$B:$F,5,0) -> 1900 | K5: =D5-E5 -> 40 | L5: =K5/D5 -> 0.8
A6: 5 | B6: C647 | C6: 23 | D6: 39 | E6: 18 | F6: Q2 2023 | G6: Below Target | H6: =VLOOKUP(B6,ColesStoreData!$B:$F,2,0) -> NSW | I6: =VLOOKUP(B6,ColesStoreData!$B:$F,3,0) -> 9308 | J6: =VLOOKUP(B6,ColesStoreData!$B:$F,5,0) -> 1700 | K6: =D6-E6 -> 21 | L6: =K6/D6 -> 0.53846154
A7: 6 | B7: C713 | C7: 38 | D7: 84 | E7: 15 | F7: Q2 2023 | G7: On Target | H7: =VLOOKUP(B7,ColesStoreData!$B:$F,2,0) -> QLD | I7: =VLOOKUP(B7,ColesStoreData!$B:$F,3,0) -> 58430 | J7: =VLOOKUP(B7,ColesStoreData!$B:$F,5,0) -> 2500 | K7: =D7-E7 -> 69 | L7: =K7/D7 -> 0.82142857
A8: 7 | B8: C308 | C8: 31 | D8: 55 | E8: 10 | F8: Q1 2023 | G8: On Target | H8: =VLOOKUP(B8,ColesStoreData!$B:$F,2,0) -> VIC | I8: =VLOOKUP(B8,ColesStoreData!$B:$F,3,0) -> 38603 | J8: =VLOOKUP(B8,ColesStoreData!$B:$F,5,0) -> 2500 | K8: =D8-E8 -> 45 | L8: =K8/D8 -> 0.81818182
A9: 8 | B9: C494 | C9: 38 | D9: 44 | E9: 8 | F9: Q1 2023 | G9: Below Target | H9: =VLOOKUP(B9,ColesStoreData!$B:$F,2,0) -> QLD | I9: =VLOOKUP(B9,ColesStoreData!$B:$F,3,0) -> 9545 | J9: =VLOOKUP(B9,ColesStoreData!$B:$F,5,0) -> 1700 | K9: =D9-E9 -> 36 | L9: =K9/D9 -> 0.81818182
A10: 9 | B10: C656 | C10: 30 | D10: 39 | E10: 10 | F10: Q2 2023 | G10: Below Target | H10: =VLOOKUP(B10,ColesStoreData!$B:$F,2,0) -> VIC | I10: =VLOOKUP(B10,ColesStoreData!$B:$F,3,0) -> 9357 | J10: =VLOOKUP(B10,ColesStoreData!$B:$F,5,0) -> 1700 | K10: =D10-E10 -> 29 | L10: =K10/D10 -> 0.74358974
A11: 10 | B11: C280 | C11: 44 | D11: 26 | E11: 15 | F11: Q1 2023 | G11: Below Target | H11: =VLOOKUP(B11,ColesStoreData!$B:$F,2,0) -> WA | I11: =VLOOKUP(B11,ColesStoreData!$B:$F,3,0) -> 8389 | J11: =VLOOKUP(B11,ColesStoreData!$B:$F,5,0) -> 1700 | K11: =D11-E11 -> 11 | L11: =K11/D11 -> 0.42307692
A12: 11 | B12: C738 | C12: 34 | D12: 29 | E12: 13 | F12: Q1 2023 | G12: Below Target | H12: =VLOOKUP(B12,ColesStoreData!$B:$F,2,0) -> VIC | I12: =VLOOKUP(B12,ColesStoreData!$B:$F,3,0) -> 8953 | J12: =VLOOKUP(B12,ColesStoreData!$B:$F,5,0) -> 1700 | K12: =D12-E12 -> 16 | L12: =K12/D12 -> 0.55172414
A13: 12 | B13: C164 | C13: 49 | D13: 45 | E13: 9 | F13: Q2 2023 | G13: Below Target | H13: =VLOOKUP(B13,ColesStoreData!$B:$F,2,0) -> ACT | I13: =VLOOKUP(B13,ColesStoreData!$B:$F,3,0) -> 7927 | J13: =VLOOKUP(B13,ColesStoreData!$B:$F,5,0) -> 1900 | K13: =D13-E13 -> 36 | L13: =K13/D13 -> 0.8
... A612: 682 | B612: C249 | C612: 36 | D612: 40 | E612: 8 | F612: Q2 2023 | G612: Below Target | H612: =VLOOKUP(B612,ColesStoreData!$B:$F,2,0) -> VIC | I612: =VLOOKUP(B612,ColesStoreData!$B:$F,3,0) -> 7063 | J612: =VLOOKUP(B612,ColesStoreData!$B:$F,5,0) -> 1700 | K612: =D612-E612 -> 32 | L612: =K612/D612 -> 0.8

Sheet Pivot Table
A3: Row Labels | B3: Sum of Profit | C3: Sum of Gross_Sale
A4: ACT | B4: 102 | C4: 115
A5: NSW | B5: 4715 | C5: 5972
A6: QLD | B6: 1980 | C6: 2363
A7: SA | B7: 96 | C7: 114
A8: TAS | B8: 71 | C8: 78
A9: VIC | B9: 3448 | C9: 4315
A10: WA | B10: 674 | C10: 793
A11: Grand Total | B11: 11086 | C11: 13750
A28: Row Labels | B28: Sum of Gross_Sale | C28: Count of Coles_StoreIDNo
A29: On Target | B29: 13750 | C29: 277
A30: Grand Total | B30: 13750 | C30: 277
A49: Sum of Gross_Sale | B49: Column Labels
A50: Row Labels | B50: Below Target | C50: On Target | D50: Grand Total
A51: Q1 2023 | B51: 6043 | C51: 7091 | D51: 13134
A52: Q2 2023 | B52: 6291 | C52: 6659 | D52: 12950
A53: Grand Total | B53: 12334 | C53: 13750 | D53: 26084

Sheet Dashboard
A1: Coles Supermarket Sales Dashboard — Australia 2023
